{"metadata": {"dbt_schema_version": "https://schemas.getdbt.com/dbt/run-results/v4.json", "dbt_version": "1.5.3", "generated_at": "2023-07-18T21:04:07.180020Z", "invocation_id": "3939d115-2e60-4c2d-8821-e09fe8e5fad8", "env": {}}, "results": [{"status": "success", "timing": [{"name": "compile", "started_at": "2023-07-18T21:03:58.286396Z", "completed_at": "2023-07-18T21:03:58.303668Z"}, {"name": "execute", "started_at": "2023-07-18T21:03:58.305631Z", "completed_at": "2023-07-18T21:03:59.455247Z"}], "thread_id": "Thread-1 (worker)", "execution_time": 1.3068504333496094, "adapter_response": {"_message": "SUCCESS 1", "code": "SUCCESS", "rows_affected": 1, "query_id": "01adb76f-0000-666f-0005-441e000163ee"}, "message": "SUCCESS 1", "failures": null, "unique_id": "model.dbtproj.dim_hosts_cleansed"}, {"status": "success", "timing": [{"name": "compile", "started_at": "2023-07-18T21:03:59.613473Z", "completed_at": "2023-07-18T21:03:59.637257Z"}, {"name": "execute", "started_at": "2023-07-18T21:03:59.639930Z", "completed_at": "2023-07-18T21:04:01.236635Z"}], "thread_id": "Thread-1 (worker)", "execution_time": 1.7102081775665283, "adapter_response": {"_message": "SUCCESS 1", "code": "SUCCESS", "rows_affected": 1, "query_id": "01adb770-0000-6667-0005-441e00015472"}, "message": "SUCCESS 1", "failures": null, "unique_id": "model.dbtproj.dim_listings_cleansed"}, {"status": "success", "timing": [{"name": "compile", "started_at": "2023-07-18T21:04:01.337110Z", "completed_at": "2023-07-18T21:04:01.369722Z"}, {"name": "execute", "started_at": "2023-07-18T21:04:01.374779Z", "completed_at": "2023-07-18T21:04:04.345934Z"}], "thread_id": "Thread-1 (worker)", "execution_time": 3.083752393722534, "adapter_response": {"_message": "SUCCESS 0", "code": "SUCCESS", "rows_affected": 0, "query_id": "01adb770-0000-666f-0005-441e00016402"}, "message": "SUCCESS 0", "failures": null, "unique_id": "model.dbtproj.fct_reviews"}, {"status": "success", "timing": [{"name": "compile", "started_at": "2023-07-18T21:04:04.436594Z", "completed_at": "2023-07-18T21:04:04.449260Z"}, {"name": "execute", "started_at": "2023-07-18T21:04:04.450406Z", "completed_at": "2023-07-18T21:04:07.060004Z"}], "thread_id": "Thread-1 (worker)", "execution_time": 2.709141492843628, "adapter_response": {"_message": "SUCCESS 1", "code": "SUCCESS", "rows_affected": 1, "query_id": "01adb770-0000-6667-0005-441e00015476"}, "message": "SUCCESS 1", "failures": null, "unique_id": "model.dbtproj.dim_listings_w_hosts"}], "elapsed_time": 11.412225008010864, "args": {"quiet": false, "exclude": [], "vars": {}, "partial_parse": true, "cache_selected_only": false, "profiles_dir": "C:\\Users\\ApurvaJoshi\\.dbt", "defer": false, "log_level_file": "debug", "indirect_selection": "eager", "use_colors_file": true, "log_path": "C:\\Users\\ApurvaJoshi\\Desktop\\dbtcourse\\dbtproj\\logs", "static_parser": true, "enable_legacy_logger": false, "favor_state": false, "printer_width": 80, "macro_debugging": false, "which": "run", "log_format": "default", "log_format_file": "debug", "populate_cache": true, "send_anonymous_usage_stats": true, "project_dir": "C:\\Users\\ApurvaJoshi\\Desktop\\dbtcourse\\dbtproj", "select": [], "strict_mode": false, "introspect": true, "version_check": true, "print": true, "log_level": "info", "use_colors": true, "warn_error_options": {"include": [], "exclude": []}, "write_json": true}}